plpy_ext/__init__.py
plpy_ext-0.0.11.dist-info/METADATA
plpy_ext-0.0.11.dist-info/WHEEL
plpy_ext-0.0.11.dist-info/top_level.txt
plpy_ext-0.0.11.dist-info/RECORD
