Metadata-Version: 2.1
Name: plpy-ext
Version: 0.0.11
Summary: Some extensions for plpython3u.
Home-page: https://pypi.org/project/plpy-ext/
Author: Filantus
Author-email: filantus@mail.ru
License: GPL
Platform: UNKNOWN
Classifier: Intended Audience :: Developers
Classifier: License :: OSI Approved :: GNU General Public License (GPL)
Classifier: Programming Language :: Python :: 3.5
Classifier: Operating System :: OS Independent
